pyturtle3d-1.0.0.dist-info/licenses/LICENSE
turtle3d/__init__.py
turtle3d/camera.py
turtle3d/collision.py
turtle3d/engine.py
turtle3d/texture.py
turtle3d/vector.py
pyturtle3d-1.0.0.dist-info/METADATA
pyturtle3d-1.0.0.dist-info/WHEEL
pyturtle3d-1.0.0.dist-info/top_level.txt
pyturtle3d-1.0.0.dist-info/RECORD
